<?xml version='1.0' encoding='utf-8'?>
<Section name="section_1" icon="section_1_image.jpg">
   <Row width="6">
      <Column width = "3">
       <Text text="section_1_text"/>
       <Image src="public/logo.jpg"/>
       <Text text="section_2_text"/>
      </Column> 
      <Column width = "3">
       <Text text="section_1_c_text"/>
       <Image src="src/server/public/logo2.jpg"/>
      </Column>  
   </Row>
   <Row width="6">
      <Column width = "6">
       <Text text="section_2_text"/>
       <Image src="src/server/public/logo3.jpg"/>
      </Column>  
   </Row>
</Section>